wishbone_slave.v
module wishbone_slave(
    input clk,
    input rst,
    input cyc,
    input stb,
    input we,
    input [7:0] adr,
    input [7:0] dat_o,

    output reg ack,
    output reg [7:0] dat_i
);

reg [7:0] memory [0:255];

always @(posedge clk or posedge rst)
begin
    if (rst)
    begin
        ack <= 0;
    end
    else
    begin
        if (cyc && stb)
        begin
            ack <= 1;

            if (we)
                memory[adr] <= dat_o;   
            else
                dat_i <= memory[adr];   
        end
        else
            ack <= 0;
    end
end

endmodule

wishbone_master.v
module wishbone_master(
    input clk,
    input rst,
    input ack,
    input [7:0] dat_i,
    input start,
    input [7:0] adr_in,
    input [7:0] dat_in,

    output reg cyc,
    output reg stb,
    output reg we,
    output reg [7:0] dat_o,
    output reg [7:0] adr,
    output reg busy
);

always @(posedge clk or posedge rst)
begin
    if (rst)
    begin
        cyc <= 0;
        stb <= 0;
        we <= 0;
        adr <= 0;
        dat_o <= 0;
        busy <= 0;
    end
    else
    begin
        if (!busy && start)
        begin
            cyc <= 1;
            stb <= 1;
            we <= 1;          // write operation
            adr <= adr_in;
            dat_o <= dat_in;
            busy <= 1;
        end
        else if (busy && ack)
        begin
            cyc <= 0;
            stb <= 0;
            busy <= 0;
        end
    end
end

endmodule

wishbone_tb.v
`include "wishbone_master.v"
`include "wishbone_slave.v"
`timescale 1ns/1ps
module wishbone_tb;

reg clk;
reg rst;
reg start;
reg [7:0] adr_in;
reg [7:0] wr_dat_in;

wire cyc;
wire stb;
wire we;
wire ack;
wire busy;

wire [7:0] adr;
wire [7:0] dat_o;
wire [7:0] dat_i;

// Instantiate Master
wishbone_master master (
    .clk(clk),
    .rst(rst),
    .ack(ack),
    .dat_i(dat_i),
    .start(start),
    .adr_in(adr_in),
    .dat_in(wr_dat_in),
    .cyc(cyc),
    .stb(stb),
    .we(we),
    .dat_o(dat_o),
    .adr(adr),
    .busy(busy)
);

// Instantiate Slave
wishbone_slave slave (
    .clk(clk),
    .rst(rst),
    .cyc(cyc),
    .stb(stb),
    .we(we),
    .adr(adr),
    .dat_o(dat_o),
    .ack(ack),
    .dat_i(dat_i)
);

always #5 clk = ~clk;   

always @(posedge clk)
begin
    $display("%0t\t%0b    %0b   %0b   %0b  %0b   0x%0h  0x%0h  0x%0h", $time, busy, cyc, stb, we, ack, adr, dat_o, dat_i);
end

initial
begin
    $dumpfile("wishbone.vcd");
    $dumpvars(0, wishbone_tb);

    clk = 0;
    rst = 1;
    start = 0;
    adr_in = 8'h00;
    wr_dat_in = 8'h00;

    $display("Time\tbusy cyc stb we ack adr dat_o dat_i");

    #20 rst = 0;

    // Write 0xAA to address 0x10
    @(posedge clk);
    adr_in = 8'h10;
    wr_dat_in = 8'hAA;
    start = 1;
    @(posedge clk);
    start = 0;

    wait (ack == 1);
    wait (ack == 0);

    // Write 0x55 to address 0x20
    @(posedge clk);
    adr_in = 8'h20;
    wr_dat_in = 8'h55;
    start = 1;
    @(posedge clk);
    start = 0;

    wait (ack == 1);
    wait (ack == 0);
    repeat (3) @(posedge clk);

    $display("Memory[0x10]=0x%0h", slave.memory[8'h10]);
    $display("Memory[0x20]=0x%0h", slave.memory[8'h20]);

    #10;
    $finish;
end

endmodule

wishbone.vcd
$date
	Thu Apr 30 18:30:19 2026
$end
$version
	Icarus Verilog
$end
$timescale
	1ps
$end
$scope module wishbone_tb $end
$var wire 1 ! we $end
$var wire 1 " stb $end
$var wire 8 # dat_o [7:0] $end
$var wire 8 $ dat_i [7:0] $end
$var wire 1 % cyc $end
$var wire 1 & busy $end
$var wire 8 ' adr [7:0] $end
$var wire 1 ( ack $end
$var reg 8 ) adr_in [7:0] $end
$var reg 1 * clk $end
$var reg 1 + rst $end
$var reg 1 , start $end
$var reg 8 - wr_dat_in [7:0] $end
$scope module master $end
$var wire 8 . adr_in [7:0] $end
$var wire 1 * clk $end
$var wire 8 / dat_in [7:0] $end
$var wire 1 + rst $end
$var wire 1 , start $end
$var wire 8 0 dat_i [7:0] $end
$var wire 1 ( ack $end
$var reg 8 1 adr [7:0] $end
$var reg 1 & busy $end
$var reg 1 % cyc $end
$var reg 8 2 dat_o [7:0] $end
$var reg 1 " stb $end
$var reg 1 ! we $end
$upscope $end
$scope module slave $end
$var wire 8 3 adr [7:0] $end
$var wire 1 * clk $end
$var wire 1 % cyc $end
$var wire 8 4 dat_o [7:0] $end
$var wire 1 + rst $end
$var wire 1 " stb $end
$var wire 1 ! we $end
$var reg 1 ( ack $end
$var reg 8 5 dat_i [7:0] $end
$upscope $end
$upscope $end
$enddefinitions $end
$comment Show the parameter values. $end
$dumpall
$end
#0
$dumpvars
bx 5
b0 4
b0 3
b0 2
b0 1
bx 0
b0 /
b0 .
b0 -
0,
1+
0*
b0 )
0(
b0 '
0&
0%
bx $
b0 #
0"
0!
$end
#5000
1*
#10000
0*
#15000
1*
#20000
0*
0+
#25000
1&
b10101010 #
b10101010 2
b10101010 4
b10000 '
b10000 1
b10000 3
1!
1"
1%
1,
b10101010 -
b10101010 /
b10000 )
b10000 .
1*
#30000
0*
#35000
1(
0,
1*
#40000
0*
#45000
0&
0"
0%
1*
#50000
0*
#55000
0(
1*
#60000
0*
#65000
1&
b1010101 #
b1010101 2
b1010101 4
b100000 '
b100000 1
b100000 3
1"
1%
1,
b1010101 -
b1010101 /
b100000 )
b100000 .
1*
#70000
0*
#75000
1(
0,
1*
#80000
0*
#85000
0&
0"
0%
1*
#90000
0*
#95000
0(
1*
